Workbook

Sheet Setup
B2: 01 | C2: — SETUP
B3: Fill in the amber cells — do not edit white formula cells
B7: 01 — PRACTICE INFORMATION
B9: Practice Name | F9: [Your Practice Name]
B10: Tagline / Descriptor | F10: [e.g., Bookkeeping for service businesses]
B11: Owner / Bookkeeper Name | F11: [Your Name]
B12: Email Address | F12: [your@email.com]
B13: Phone Number | F13: [Your Phone]
B14: Website / Portal URL | F14: [https://yoursite.com]
B15: Bookkeeping Software Used | F15: [QuickBooks Online / Xero / Wave / Other]
B16: Currency Symbol | F16: €
B17: Monthly Close Day (of following month) | F17: 15
B18: Fiscal Year End Month | F18: December
B20: 02 — SERVICE TIERS
B22: Tier Name | C22: Monthly Transactions | D22: Accounts | E22: Monthly Fee (€) | F22: Hourly Rate (€)
B23: Essentials | C23: 100 | D23: 3 | E23: 650 | F23: 75
B24: Growth | C24: 300 | D24: 6 | E24: 1200 | F24: 85
B25: Advanced | C25: 600 | D25: 12 | E25: 2200 | F25: 100

Sheet Client CRM
B2: 02 | C2: — CLIENT CRM
B3: Master record for all active and former clients
B6: Client Name | C6: Status | D6: Entity Type | E6: Software | F6: Monthly Fee (€) | G6: Close Day | H6: Primary Contact | I6: Email | J6: Tax Preparer | K6: Start Date | L6: Service Package | M6: Notes
B7: Harbor Design LLC | C7: Active | D7: LLC | E7: QuickBooks Online | F7: 850 | G7: 15 | H7: Alex Morgan | I7: alex@example.com | J7: [Tax Preparer] | K7: 2025-01-01 | L7: Growth
B8: Oak & Pine Co. | C8: Active | D8: S-Corp | E8: Xero | F8: 1200 | G8: 15 | H8: Jamie Chen | I8: jamie@example.com | J8: [Tax Preparer] | K8: 2025-03-01 | L8: Advanced
B9: [Client Name] | C9: Active | D9: [Entity] | E9: [Software] | F9: 0 | G9: 15 | H9: [Contact] | I9: [Email] | J9: [Tax Preparer] | L9: Essentials
B11: TOTAL MONTHLY RECURRING REVENUE | F11: =SUMIF(C7:C200,"Active",F7:F200)

Sheet Lead Pipeline
B2: 03 | C2: — LEAD PIPELINE
B3: Track every prospect from first contact to closed deal
B6: Lead / Contact Name | C6: Company | D6: Stage | E6: Source | F6: Est. Monthly Fee (€) | G6: Cleanup Est. (€) | H6: Next Action | I6: Next Action Date | J6: Email | K6: Notes
B7: Jamie Chen | C7: Oak & Pine Co. | D7: Diagnostic Scheduled | E7: Referral | F7: 1200 | G7: 2400 | H7: Run diagnostic | I7: 2026-07-03 | J7: jamie@example.com
B8: [Lead Name] | C8: [Company] | D8: New Inquiry | E8: [Source] | F8: 0 | G8: 0 | H8: [Action] | J8: [Email]
B10: TOTAL PIPELINE VALUE (MONTHLY) | E10: =SUMIF(D7:D200,"<>Closed Lost",F7:F200)
B11: OPEN LEAD COUNT | D11: =COUNTIF(D7:D200,"<>Closed Lost")-COUNTIF(D7:D200,"Closed Won")

Sheet Pricing Calculator
B2: 04 | C2: — PRICING CALCULATOR
B3: Calculate client fees based on scope — fill amber cells
B7: 01 — CLIENT INPUTS
B9: Monthly Bank Transactions | H9: 150
B10: Number of Bank Accounts | H10: 3
B11: Number of Credit Cards | H11: 2
B12: Has Payroll? (1=Yes / 0=No) | H12: 0
B13: Has Sales Tax / VAT? (1=Yes / 0=No) | H13: 0
B14: Has Multi-Entity / Class Tracking? (1=Yes / 0=No) | H14: 0
B15: Has Foreign Currency? (1=Yes / 0=No) | H15: 0
B16: Cleanup Months Needed | H16: 0
B18: 02 — CALCULATED FEES
B20: Base Monthly Fee | H20: =IF(H9<=100,650,IF(H9<=300,1200,2200))
B21: Payroll Add-On | H21: =IF(H12=1,150,0)
B22: Sales Tax / VAT Add-On | H22: =IF(H13=1,100,0)
B23: Multi-Entity Add-On | H23: =IF(H14=1,300,0)
B24: Foreign Currency Add-On | H24: =IF(H15=1,200,0)
B25: Cleanup Project Estimate | H25: =H16*400
B26: RECOMMENDED MONTHLY FEE | H26: =SUM(H20:H25)-H25
B27: CLEANUP PROJECT ESTIMATE (one-time) | H27: =H26

Sheet Monthly Close
B2: 05 | C2: — MONTHLY CLOSE TRACKER
B3: Track close status for every client each period
B6: Period | C6: Client | D6: Status | E6: Owner | F6: Bank Rec. | G6: Card Rec. | H6: Questions Sent | I6: Questions Answered | J6: Reports Delivered | K6: Due Date | L6: Review Notes
B7: 2026-07 | C7: Harbor Design LLC | D7: In Progress | E7: [OWNER] | F7: Yes | G7: No | H7: No | I7: No | J7: No | K7: 2026-08-15
B8: 2026-07 | C8: Oak & Pine Co. | D8: Not Started | E8: [OWNER] | F8: No | G8: No | H8: No | I8: No | J8: No | K8: 2026-08-15
B9: 2026-07 | C9: [Client Name] | D9: Not Started | E9: [OWNER] | F9: No | G9: No | H9: No | I9: No | J9: No

Sheet Invoice Tracker
B2: 06 | C2: — INVOICE TRACKER
B3: Track all invoices, payment status, and outstanding balances
B6: Invoice # | C6: Client | D6: Issue Date | E6: Due Date | F6: Amount (€) | G6: Status | H6: Paid Date | I6: Service Period | J6: Method | K6: Notes
B7: INV-001 | C7: Harbor Design LLC | D7: 2026-07-01 | E7: 2026-07-08 | F7: 850 | G7: Paid | H7: 2026-07-05 | I7: 2026-07 | J7: Bank Transfer
B8: INV-002 | C8: Oak & Pine Co. | D8: 2026-07-01 | E8: 2026-07-08 | F8: 1200 | G8: Paid | H8: 2026-07-03 | I8: 2026-07 | J8: Bank Transfer
B9: INV-003 | C9: [Client Name] | D9: 2026-08-01 | E9: 2026-08-08 | F9: 0 | G9: Draft | I9: 2026-08
B11: TOTAL INVOICED | D11: =SUMIF(G7:G500,"<>Void",F7:F500)
B12: TOTAL PAID | E12: =SUMIF(G7:G500,"Paid",F7:F500)
B13: TOTAL OUTSTANDING | F13: =SUMIF(G7:G500,"Sent",F7:F500)+SUMIF(G7:G500,"Overdue",F7:F500)

Sheet Tax Documents
B2: 07 | C2: — TAX DOCUMENTS
B3: Track year-end document collection status per client
B6: Client | C6: Fiscal Year | D6: Income Docs | E6: Bank Stmts | F6: Payroll | G6: Expenses | H6: Assets/Debt | I6: Tax/Compliance | J6: Owner Activity | K6: Package Delivered | L6: Tax Preparer | M6: Notes
B7: Harbor Design LLC | C7: 2025 | D7: Received | E7: Received | F7: N/A | G7: Received | H7: Received | I7: Pending | J7: N/A | K7: No | L7: [Tax Preparer]
B8: Oak & Pine Co. | C8: 2025 | D8: Pending | E8: Pending | F8: Pending | G8: Pending | H8: Pending | I8: Pending | J8: Pending | K8: No | L8: [Tax Preparer]

Sheet Capacity Planner
B2: 08 | C2: — CAPACITY PLANNER
B3: Plan your available hours vs. committed client time
B7: 01 — WEEKLY CAPACITY INPUTS
B9: Total available hours per week | G9: 40
B10: Admin / sales hours per week | G10: 8
B11: Buffer / training hours per week | G11: 2
B12: Billable hours available per week | G12: =G9-G10-G11
B14: 02 — CLIENT TIME COMMITMENTS
B16: Client | C16: Package | D16: Avg Hours/Month | E16: Hours/Week | F16: Notes
B17: Harbor Design LLC | C17: Growth | D17: 8 | E17: =D17/4
B18: Oak & Pine Co. | C18: Advanced | D18: 12 | E18: =D18/4
B19: [Client Name] | C19: Essentials | D19: 5 | E19: =D19/4
B21: TOTAL COMMITTED HOURS / WEEK | E21: =SUM(E17:E20)

Sheet Dashboard
A2: BOOKKEEPER PRACTICE DASHBOARD
A3: v2.0 · Consulting Edition · Live data from all sheets
A6: ACTIVE CLIENTS | D6: MONTHLY RECURRING REVENUE | G6: OPEN PIPELINE VALUE | J6: ACTIVE LEADS | M6: TOTAL INVOICED (YTD) | P6: CLOSES IN PROGRESS
A7: =COUNTIF('Client CRM'!C:C,"Active") | D7: =SUMIF('Client CRM'!C:C,"Active",'Client CRM'!F:F) | G7: =SUMIF('Lead Pipeline'!D:D,"<>Closed Lost",'Lead Pipeline'!F:F) | J7: =COUNTIF('Lead Pipeline'!D:D,"<>Closed Lost")-COUNTIF('Lead Pipeline'!D:D,"Closed Won") | M7: =SUMIF('Invoice Tracker'!G:G,"<>Void",'Invoice Tracker'!F:F) | P7: =COUNTIF('Monthly Close'!D:D,"In Progress")
A8: from Client CRM | D8: total active fees | G8: est. monthly from leads | J8: in pipeline | M8: all non-void invoices | P8: this month
A13: 01 — ACTIVE CLIENT SNAPSHOT
A14: Client | C14: Package | E14: Fee (€) | G14: Close Day | I14: Contact | K14: Software
A15: =IFERROR(INDEX('Client CRM'!B:B,MATCH("Active",'Client CRM'!C:C,0)+0),"") | C15: =IFERROR(INDEX('Client CRM'!L:L,MATCH("Active",'Client CRM'!C:C,0)+0),"") | E15: =IFERROR(INDEX('Client CRM'!F:F,MATCH("Active",'Client CRM'!C:C,0)+0),"") | G15: =IFERROR(INDEX('Client CRM'!G:G,MATCH("Active",'Client CRM'!C:C,0)+0),"") | I15: =IFERROR(INDEX('Client CRM'!H:H,MATCH("Active",'Client CRM'!C:C,0)+0),"") | K15: =IFERROR(INDEX('Client CRM'!E:E,MATCH("Active",'Client CRM'!C:C,0)+0),"")
A16: =IFERROR(INDEX('Client CRM'!B:B,MATCH("Active",'Client CRM'!C:C,0)+1),"") | C16: =IFERROR(INDEX('Client CRM'!L:L,MATCH("Active",'Client CRM'!C:C,0)+1),"") | E16: =IFERROR(INDEX('Client CRM'!F:F,MATCH("Active",'Client CRM'!C:C,0)+1),"") | G16: =IFERROR(INDEX('Client CRM'!G:G,MATCH("Active",'Client CRM'!C:C,0)+1),"") | I16: =IFERROR(INDEX('Client CRM'!H:H,MATCH("Active",'Client CRM'!C:C,0)+1),"") | K16: =IFERROR(INDEX('Client CRM'!E:E,MATCH("Active",'Client CRM'!C:C,0)+1),"")
A17: =IFERROR(INDEX('Client CRM'!B:B,MATCH("Active",'Client CRM'!C:C,0)+2),"") | C17: =IFERROR(INDEX('Client CRM'!L:L,MATCH("Active",'Client CRM'!C:C,0)+2),"") | E17: =IFERROR(INDEX('Client CRM'!F:F,MATCH("Active",'Client CRM'!C:C,0)+2),"") | G17: =IFERROR(INDEX('Client CRM'!G:G,MATCH("Active",'Client CRM'!C:C,0)+2),"") | I17: =IFERROR(INDEX('Client CRM'!H:H,MATCH("Active",'Client CRM'!C:C,0)+2),"") | K17: =IFERROR(INDEX('Client CRM'!E:E,MATCH("Active",'Client CRM'!C:C,0)+2),"")
A19: 02 — MONTHLY CLOSE STATUS — CURRENT PERIOD
A20: Client | C20: Status | E20: Bank Rec | G20: Reports Delivered | I20: Due Date | K20: Owner
A21: =IFERROR(INDEX('Monthly Close'!C:C,1+1),"") | C21: =IFERROR(INDEX('Monthly Close'!D:D,1+1),"") | E21: =IFERROR(INDEX('Monthly Close'!F:F,1+1),"") | G21: =IFERROR(INDEX('Monthly Close'!J:J,1+1),"") | I21: =IFERROR(INDEX('Monthly Close'!K:K,1+1),"") | K21: =IFERROR(INDEX('Monthly Close'!E:E,1+1),"")
A22: =IFERROR(INDEX('Monthly Close'!C:C,2+1),"") | C22: =IFERROR(INDEX('Monthly Close'!D:D,2+1),"") | E22: =IFERROR(INDEX('Monthly Close'!F:F,2+1),"") | G22: =IFERROR(INDEX('Monthly Close'!J:J,2+1),"") | I22: =IFERROR(INDEX('Monthly Close'!K:K,2+1),"") | K22: =IFERROR(INDEX('Monthly Close'!E:E,2+1),"")
A23: =IFERROR(INDEX('Monthly Close'!C:C,3+1),"") | C23: =IFERROR(INDEX('Monthly Close'!D:D,3+1),"") | E23: =IFERROR(INDEX('Monthly Close'!F:F,3+1),"") | G23: =IFERROR(INDEX('Monthly Close'!J:J,3+1),"") | I23: =IFERROR(INDEX('Monthly Close'!K:K,3+1),"") | K23: =IFERROR(INDEX('Monthly Close'!E:E,3+1),"")

Sheet Instructions
B2: 09 | C2: — INSTRUCTIONS
B3: How to use every sheet in this dashboard
B6: 01 — SETUP | E6: Fill in the amber cells only. White cells contain formulas that reference Setup data — do not edit them. Changes to Practice Name and pricing cascade to the Pricing Calculator.
B8: 02 — CLIENT CRM | E8: Add one row per client. The Status column (Active/Churned/On Hold) drives the Dashboard KPIs. Use the Package dropdown to match your service tiers. The MRR formula at the bottom sums only Active clients.
B10: 03 — LEAD PIPELINE | E10: Add a row for each prospect. The Pipeline Value at the bottom sums all leads not marked Closed Lost. Move Stage through the dropdown — from New Inquiry to Closed Won.
B12: 04 — PRICING CALCULATOR | E12: Enter the prospect's details in the amber cells. The calculator produces a recommended monthly fee and cleanup estimate. Use it during diagnostic calls.
B14: 05 — MONTHLY CLOSE | E14: Add one row per client per period (e.g., "2026-07"). Use the Status and checkbox dropdowns (Yes/No) to track progress. Conditional formatting turns cells teal when complete.
B16: 06 — INVOICE TRACKER | E16: Add one row per invoice. Status drives the Outstanding balance formula at the bottom. Mark Paid invoices with the payment date. Overdue rows turn red automatically.
B18: 07 — TAX DOCUMENTS | E18: Use this sheet at year-end. One row per client per fiscal year. Track document collection across all categories. Mark items N/A if they do not apply to that client.
B20: 08 — CAPACITY PLANNER | E20: Enter your weekly available hours and admin time. Add one row per client with their average monthly hours. The sheet shows whether you are over or under capacity.
B22: 09 — DASHBOARD | E22: This sheet auto-populates from all other sheets. Do not enter data here directly. KPI cards show active clients, MRR, pipeline value, and close status in real time.
B24: 10 — INSTRUCTIONS | E24: This sheet. Reference it anytime you are unsure about a feature.
B27: TIP: Only edit cells with amber background. Never edit cells with teal or dark backgrounds — those contain formulas or are read-only display areas.
